{
  "iterationid": 1,
  "phase": "iterated",
  "hierarchy": [
    "nodeflow-local-server",
    "nodeflow-local-web",
    "nodeflow-local-common",
    "nodeflow-local-graph"
  ],
  "latest": [
    {
      "moduleid": "nodeflow-local-server",
      "iterationid": 1,
      "version": "1.70.0-runtime-stuck-dev"
    },
    {
      "moduleid": "nodeflow-local-web",
      "iterationid": 1,
      "version": "1.70.0-runtime-stuck-dev"
    },
    {
      "moduleid": "nodeflow-local-common",
      "iterationid": 1,
      "version": "1.70.0-runtime-stuck-dev"
    },
    {
      "moduleid": "nodeflow-local-graph",
      "iterationid": 1,
      "version": "1.70.0-runtime-stuck-dev"
    }
  ],
  "created": 1559314709,
  "updated": 1559314709,
  "status": "active"
}