{
  "moduleid": "repoflow-plugin-stateful",
  "type": "npm",
  "url": "github.com:vicjicaman/repoflow-plugin-stateful.git",
  "fullname": "@nebulario/repoflow-plugin-stateful",
  "iteration": {
    "mode": "prod"
  },
  "release": {
    "type": "patch"
  },
  "description": "Stateful plugin for kubernetes services",
  "created": 1567610014,
  "updated": 1567610014,
  "status": "active",
  "commit": {
    "commitid": "782f387d08d84e1c2876b5889e48d3395b25848a",
    "message": "Add stateful plugin\n"
  }
}