{
  "moduleid": "repoflow-plugin-realm",
  "type": "npm",
  "url": "github.com:vicjicaman/repoflow-plugin-realm.git",
  "fullname": "@nebulario/repoflow-plugin-realm",
  "iteration": {
    "mode": "prod"
  },
  "release": {
    "type": "patch"
  },
  "description": "Plugin for the kubernetes entities",
  "created": 1570681132,
  "updated": 1570681132,
  "status": "active",
  "commit": {
    "commitid": "902312a8f062c61ff66273b0c0ac0a8180b47674",
    "message": "Remove listener configuration for events\n"
  }
}