{
  "moduleid": "nodeflow-local-server",
  "type": "npm",
  "url": "github.com:vicjicaman/nodeflow-local-server.git",
  "fullname": "@nebulario/nodeflow-local-server",
  "iteration": {
    "mode": "prod"
  },
  "release": {
    "type": "patch"
  },
  "description": "- SSR service for repoflow tool based on common code",
  "created": 1568815300,
  "updated": 1568815300,
  "status": "active",
  "commit": {
    "commitid": "164ec7f800b58d50b08c5cc24eca1866054d772d",
    "message": "Add enable and disable functionality for performers\n"
  }
}