{
  "releaseid": "repoflow-tool-script",
  "moduleid": "core-render-stateful-server",
  "version": "1.70.3-master",
  "fullname": "@nebulario/core-render-stateful-server",
  "type": "npm",
  "url": "github.com:vicjicaman/core-render-stateful-server.git",
  "publish": null,
  "released": {
    "commitid": "f14dcba736769307578f12095fde9e00780656e7",
    "message": "ITERATION:3\n"
  },
  "mergeback": null,
  "releaseType": "patch",
  "description": "- Core server part for a stateful web app",
  "dependencies": [],
  "created": 1576944038,
  "updated": 1576944038,
  "status": "active"
}