{
  "moduleid": "repoflow-container-server",
  "releases": [
    {
      "releaseid": "public-containers"
    },
    {
      "releaseid": "compose-performers"
    },
    {
      "releaseid": "container-dependencies"
    }
  ],
  "created": 1552368255,
  "updated": 1552368255,
  "status": "active",
  "dependants": [
    {
      "moduleid": "repoflow-compose",
      "references": [
        {
          "dependencyid": "dependency|docker-compose.yml|.+web:\\s+image:(?:\\s+|)(?:.+):(.+)",
          "fullname": "repoflow/repoflow-container-server",
          "version": "1.70.2-master",
          "kind": "dependency",
          "filename": "docker-compose.yml",
          "path": ".+web:\\s+image:(?:\\s+|)(?:.+):(.+)"
        }
      ]
    }
  ],
  "dependents": [
    {
      "moduleid": "nodeflow-local-server",
      "references": [
        {
          "dependencyid": "dependency|package.json|dependencies.@nebulario/nodeflow-local-server",
          "fullname": "@nebulario/nodeflow-local-server",
          "version": "1.71.4-master",
          "kind": "app",
          "filename": "package.json",
          "path": "dependencies.@nebulario/nodeflow-local-server"
        }
      ]
    }
  ]
}