{
  "iterationid": 16,
  "phase": "releasing",
  "hierarchy": [
    "nodeflow-local-server",
    "nodeflow-local-web",
    "nodeflow-local-common",
    "nodeflow-local-graph"
  ],
  "latest": [
    {
      "moduleid": "nodeflow-local-server",
      "version": "1.0.15-runtime-rebuild-prod",
      "iterationid": 16
    },
    {
      "moduleid": "nodeflow-local-web",
      "version": "1.0.14-runtime-rebuild-prod",
      "iterationid": 16
    },
    {
      "moduleid": "nodeflow-local-common",
      "version": "1.0.12-runtime-rebuild-prod",
      "iterationid": 16
    },
    {
      "moduleid": "nodeflow-local-graph",
      "version": "1.0.12-runtime-rebuild-prod",
      "iterationid": 16
    }
  ],
  "created": 1550617225,
  "updated": 1550617225,
  "status": "active"
}