{
  "moduleid": "repoflow-tool",
  "mode": "prod",
  "version": "1.70.5-resolve-workspace-prod",
  "fullname": "@nebulario/repoflow-tool",
  "type": "bundle",
  "url": "github.com:vicjicaman/repoflow-tool.git",
  "publish": null,
  "iterate": {
    "commitid": "d09baa1610aae1df104c498ed5879d6e4be6127e",
    "message": "Merge remote-tracking branch 'origin/resolve-workspace/master' into resolve-workspace/master\n"
  },
  "mergeback": null,
  "releasedOn": 6,
  "created": 1560250744,
  "updated": 1560250744,
  "status": "active"
}