{
  "releaseid": "bundle-cluster",
  "moduleid": "nodeflow-local-graph",
  "version": "1.73.3-master",
  "fullname": "@nebulario/nodeflow-local-graph",
  "type": "npm",
  "url": "github.com:vicjicaman/nodeflow-local-graph.git",
  "publish": null,
  "released": {
    "commitid": "38b20194be63224ebc4d82228bd566f431484944",
    "message": "ITERATION:1\n"
  },
  "mergeback": null,
  "releaseType": "patch",
  "description": "- GraphQL API for the workspace, instance and repositories\n- Runtime and plugins API for:\n   - Publish\n   - Run\n   - Build",
  "dependencies": [],
  "created": 1570832548,
  "updated": 1570832548,
  "status": "active"
}