{
  "moduleid": "repoflow-build-server",
  "type": "npm",
  "url": "github.com:vicjicaman/repoflow-build-server.git",
  "fullname": "@nebulario/repoflow-build-server",
  "iteration": {
    "mode": "prod"
  },
  "release": {
    "type": "patch"
  },
  "description": "Demo build server to publish packages, containers and services to kubernetes",
  "created": 1570028695,
  "updated": 1570028695,
  "status": "active",
  "commit": {
    "commitid": "4cad0138795d6650ba7838eeac4e71a2fcb8da07",
    "message": "Add update agent to realm pod and apps\n"
  }
}