{
  "status": "valid",
  "modules": [
    {
      "moduleid": "repoflow-build-server",
      "mode": "dev",
      "version": "1.0.2-build-server-services-dev",
      "type": "npm",
      "fullname": "@nebulario/repoflow-build-server",
      "repository": {
        "url": "github.com:vicjicaman/repoflow-build-server.git",
        "commitid": "3971ff92d950ac0e92d11a9c9ddf7da2a039c277",
        "message": "Set to next iteration"
      },
      "release": true
    },
    {
      "moduleid": "repoflow-plugin-container",
      "mode": "dev",
      "version": "1.0.1-build-server-services-dev",
      "type": "npm",
      "fullname": "@nebulario/repoflow-plugin-container",
      "repository": {
        "url": "github.com:vicjicaman/repoflow-plugin-container.git",
        "commitid": "051280276d488bf6b76d8bd9f3dc26c4afb4c679",
        "message": "Sync to next iteration"
      },
      "release": false
    },
    {
      "moduleid": "repoflow-plugin-npm",
      "mode": "dev",
      "version": "1.0.2-build-server-services-dev",
      "type": "npm",
      "fullname": "@nebulario/repoflow-plugin-npm",
      "repository": {
        "url": "github.com:vicjicaman/repoflow-plugin-npm.git",
        "commitid": "659276a025128cec6f40b602e253b339f20be1f7",
        "message": "Set to next iteration"
      },
      "release": true
    },
    {
      "moduleid": "core-plugin-request",
      "mode": "dev",
      "version": "1.0.1-build-server-services-dev",
      "type": "npm",
      "fullname": "@nebulario/core-plugin-request",
      "repository": {
        "url": "github.com:vicjicaman/core-plugin-request.git",
        "commitid": "bf06ff9f51a70a775235e47926fe5370144b484c",
        "message": "Add stopping plugin instead of hard stop"
      },
      "release": false
    }
  ]
}