{
  "releaseid": "container-runtime",
  "moduleid": "repoflow-plugin-container",
  "version": "1.70.14-master",
  "fullname": "@nebulario/repoflow-plugin-container",
  "type": "npm",
  "url": "github.com:vicjicaman/repoflow-plugin-container.git",
  "publish": null,
  "released": {
    "commitid": "755c41d91e82492d13d6705be5ee6fcef29bfbcb",
    "message": "ITERATION:2\n"
  },
  "mergeback": null,
  "releaseType": "patch",
  "description": "Plugin for container image with a NPM package as service",
  "dependencies": [],
  "created": 1570374102,
  "updated": 1570374102,
  "status": "active"
}