{
  "moduleid": "nodeflow-local-common",
  "mode": "prod",
  "version": "1.70.1-runtime-reference-prod",
  "fullname": "@nebulario/nodeflow-local-common",
  "type": "npm",
  "url": "github.com:vicjicaman/nodeflow-local-common.git",
  "publish": null,
  "iterate": {
    "commitid": "e77c97b8bd2c1a3e51fe5e5f15d3daeee143eefe",
    "message": "Add core-cluster package for build and run cluster plugins\n"
  },
  "mergeback": null,
  "releasedOn": 2,
  "created": 1568951719,
  "updated": 1568951719,
  "status": "active"
}